pylibob-0.1.1.dist-info/METADATA
pylibob-0.1.1.dist-info/WHEEL
pylibob-0.1.1.dist-info/licenses/LICENSE
pylibob/__init__.py
pylibob/asgi.py
pylibob/connection.py
pylibob/connection_ws.py
pylibob/event/__init__.py
pylibob/event/base.py
pylibob/event/message.py
pylibob/event/meta.py
pylibob/event/notice.py
pylibob/event/request.py
pylibob/exception.py
pylibob/impl.py
pylibob/runner.py
pylibob/segment.py
pylibob/status.py
pylibob/types.py
pylibob/utils.py
pylibob/utils.pyi
pylibob/version.py
pylibob-0.1.1.dist-info/RECORD
