Metadata-Version: 2.1
Name: pylibob
Version: 0.1.1
Summary: 另一个 LibOneBot Python 库，旨在帮助开发者实现 OneBot 12 标准。
Keywords: onebot libonebot onebot12
Author-Email: MingxuanGame <MingxuanGame@outlook.com>
License: MIT
Project-URL: Homepage, https://pylibob.mxgame.top
Project-URL: Documentation, https://pylibob.mxgame.top
Project-URL: Repository, https://github.com/Herta-villa/pylibob
Project-URL: Bug tracker, https://github.com/Herta-villa/pylibob/issues
Requires-Python: >=3.8
Requires-Dist: starlette>=0.27.0
Requires-Dist: uvicorn[standard]<1,>=0.23.2
Requires-Dist: msgspec>=0.18.2
Requires-Dist: typing_extensions<5,>=4.8.0; python_version <= "3.8"
Requires-Dist: aiohttp[speedups]<4,>=3.8.0
Requires-Dist: msgpack<2,>=1.0.7
